Metadata-Version: 2.1
Name: ExtractEmailAttachments
Version: 0.1.4
Summary: eml文件中的附件提取出来
Home-page: https://alidocs.dingtalk.com/i/p/4oJRz0VRJyvmLZMydy0mV7WvjQn7MG89
Author: zhanghao
Author-email: 17891967090@163.com
Classifier: Programming Language :: Python
Requires-Python: >=3.8
License-File: LICENSE.txt
